mfws/__init__.py
mfws/main.py
mfws/modules/__init__.py
mfws/modules/fov_aligner.py
mfws/modules/global_location.py
mfws/modules/jitter_correct.py
mfws/modules/scan_method.py
mfws/modules/stitching.py
mfws/modules/wsi_stitch.py
MFWS-0.1.1.dist-info/METADATA
MFWS-0.1.1.dist-info/WHEEL
MFWS-0.1.1.dist-info/entry_points.txt
MFWS-0.1.1.dist-info/top_level.txt
MFWS-0.1.1.dist-info/RECORD
