Metadata-Version: 2.1
Name: MFWS
Version: 0.1.1
Summary: Multiple Fast Fourier Transform weighted stitching algorithm.
Home-page: 
Author: cell bin research group
Author-email: bgi@genomics.cn
Classifier: Development Status :: 3 - Alpha
Classifier: Intended Audience :: Developers
Classifier: License :: OSI Approved :: MIT License
Requires-Python: ==3.8.*
Requires-Dist: tifffile ==2023.7.10
Requires-Dist: opencv-python ==4.12.0.88
Requires-Dist: tqdm ==4.67.1
Requires-Dist: scikit-learn ==1.3.2
Requires-Dist: scipy ==1.10.1
Requires-Dist: imagecodecs ==2023.3.16
Requires-Dist: numpy ==1.24.4
Requires-Dist: glog ==0.3.1
Requires-Dist: prettytable ==3.11.0
